MANIFEST.in
README.rst
buildout.cfg
develop.cfg
requirements.txt
setup.py
version.txt
bob/__init__.py
bob.ip.facelandmarks.egg-info/PKG-INFO
bob.ip.facelandmarks.egg-info/SOURCES.txt
bob.ip.facelandmarks.egg-info/dependency_links.txt
bob.ip.facelandmarks.egg-info/entry_points.txt
bob.ip.facelandmarks.egg-info/requires.txt
bob.ip.facelandmarks.egg-info/top_level.txt
bob/ip/__init__.py
bob/ip/facelandmarks/__init__.py
bob/ip/facelandmarks/test.py
bob/ip/facelandmarks/utils.py
bob/ip/facelandmarks/data/keypoint_model.pkl.gz
bob/ip/facelandmarks/data/lena.jpg
bob/ip/facelandmarks/data/multiple-faces.jpg
bob/ip/facelandmarks/script/__init__.py
bob/ip/facelandmarks/script/detect_landmarks.py
doc/conf.py
doc/guide.rst
doc/index.rst
doc/links.rst
doc/py_api.rst
doc/img/favicon.ico
doc/img/logo.png
doc/plot/single_face_lmks.py