Metadata-Version: 1.2
Name: bob.ip.facelandmarks
Version: 1.0.5
Summary: Bob wrapper for Menpo's face keypoint detector
Home-page: http://gitlab.idiap.ch/bob/bob.ip.facelandmarks
Author: Andre Anjos
Author-email: andre.anjos@idiap.ch
Maintainer: Sushil Bhattacharjee
Maintainer-email: sbhatta@idiap.ch
License: BSD
Keywords: bob,keypoint detection,face
Platform: UNKNOWN
Classifier: Framework :: Bob
Classifier: Development Status :: 4 - Beta
Classifier: Intended Audience :: Developers
Classifier: License :: OSI Approved :: BSD License
Classifier: Natural Language :: English
Classifier: Programming Language :: Python
Classifier: Programming Language :: Python :: 3
Classifier: Topic :: Software Development :: Libraries :: Python Modules
